{
  "themeLayoutType" : "dw9j7GwmWNUcm6oRs2tqMSIl50wALx",
  "viewType" : "custom-add-patient",
  "appPageId" : "d9c4a932-5387-4757-867b-fed2cab30e7c",
  "componentName" : "c:EmptyLayout",
  "label" : "Add Patient",
  "id" : "f18dd703-63fe-44f0-a5b5-96372a52e9b5",
  "type" : "view",
  "regions" : [ {
    "regionName" : "column1",
    "id" : "c96002e1-471e-4b23-911b-dae347ed8b2e",
    "type" : "region",
    "components" : [ {
      "componentName" : "c:AddPatientByPI",
      "componentAttributes" : { },
      "renderPriority" : "NEUTRAL",
      "renditionMap" : { },
      "id" : "9c8fbfd3-8120-4506-90d5-ab0bc87622b2",
      "type" : "component",
      "renditions" : [ ]
    } ]
  }, {
    "regionName" : "sfdcHiddenRegion",
    "id" : "3a6ce898-a6cd-4c25-9967-f9adbf4a66b2",
    "type" : "region",
    "components" : [ {
      "componentName" : "forceCommunity:seoAssistant",
      "componentAttributes" : {
        "metaTags" : "",
        "description" : "",
        "title" : "Add Patient"
      },
      "renderPriority" : "NEUTRAL",
      "renditionMap" : { },
      "id" : "1249026a-2488-478d-804c-c2a1d22d85aa",
      "type" : "component",
      "renditions" : [ ]
    } ]
  } ]
}