{
  "themeLayoutType" : "O3BaUt1WFPg1Lbs4TSli1UrNxJ1ZUS",
  "viewType" : "custom-task-reminder-detail",
  "appPageId" : "f7dbe0ac-e464-4120-9569-94d8d9fac739",
  "componentName" : "c:EmptyLayout",
  "label" : "Task Reminder Detail",
  "id" : "4c3e1d9f-8cf9-4f26-9209-132ececdbb9f",
  "type" : "view",
  "regions" : [ {
    "regionName" : "column1",
    "id" : "c53bb5e5-dc85-428c-8eeb-51c4e0c353ce",
    "type" : "region",
    "components" : [ {
      "componentName" : "c:TaskReminderDetail",
      "componentAttributes" : { },
      "renderPriority" : "NEUTRAL",
      "renditionMap" : { },
      "id" : "655c3616-4695-4dc8-898b-6930bf335c44",
      "type" : "component",
      "renditions" : [ ]
    } ]
  }, {
    "regionName" : "sfdcHiddenRegion",
    "id" : "0728965d-8527-4303-bb43-ec319d35705d",
    "type" : "region",
    "components" : [ {
      "componentName" : "forceCommunity:seoAssistant",
      "componentAttributes" : {
        "metaTags" : "",
        "description" : "",
        "title" : "Task Reminder Detail"
      },
      "renderPriority" : "NEUTRAL",
      "renditionMap" : { },
      "id" : "68d34595-5a93-4e71-999d-e52acd804c08",
      "type" : "component",
      "renditions" : [ ]
    } ]
  } ]
}