{
  "appPageId" : "0c5e71c7-37e7-4704-a584-cd6399619ee3",
  "componentName" : "siteforce:sldsOneColLayout",
  "id" : "56e585eb-40b0-4504-9164-6739969546b2",
  "label" : "Check Password",
  "regions" : [ {
    "components" : [ {
      "componentAttributes" : {
        "richTextValue" : "<div style=\"text-align: center;\"><a href=\"./\">Back to login</a></div>"
      },
      "componentName" : "forceCommunity:richTextInline",
      "id" : "25b40486-7d76-4675-8c5a-cb1e0a669524",
      "renderPriority" : "NEUTRAL",
      "renditionMap" : { },
      "type" : "component"
    } ],
    "id" : "36c816c6-84f9-4b89-b167-614b221aafdc",
    "regionName" : "content",
    "type" : "region"
  }, {
    "components" : [ {
      "componentAttributes" : {
        "description" : "",
        "metaTags" : "",
        "title" : "Check Password"
      },
      "componentName" : "forceCommunity:seoAssistant",
      "id" : "0ba778d5-d0fd-40c3-ab7d-f653e9cd05c7",
      "renditionMap" : { },
      "type" : "component"
    } ],
    "id" : "bc2b9592-9bac-402d-ab71-eeb112829a46",
    "regionName" : "sfdcHiddenRegion",
    "type" : "region"
  } ],
  "themeLayoutType" : "vlFHBpLpECaLjImgddfCXjWzZHN1T2",
  "type" : "view",
  "viewType" : "check-password"
}